odoo10_addon_partner_contact_gender-10.0.1.1.0-py2.7-nspkg.pth
odoo10_addon_partner_contact_gender-10.0.1.1.0.dist-info/top_level.txt
odoo10_addon_partner_contact_gender-10.0.1.1.0.dist-info/WHEEL
odoo10_addon_partner_contact_gender-10.0.1.1.0.dist-info/RECORD
odoo10_addon_partner_contact_gender-10.0.1.1.0.dist-info/metadata.json
odoo10_addon_partner_contact_gender-10.0.1.1.0.dist-info/DESCRIPTION.rst
odoo10_addon_partner_contact_gender-10.0.1.1.0.dist-info/METADATA
odoo10_addon_partner_contact_gender-10.0.1.1.0.dist-info/namespace_packages.txt
odoo/addons/partner_contact_gender/__manifest__.py
odoo/addons/partner_contact_gender/hooks.py
odoo/addons/partner_contact_gender/__init__.py
odoo/addons/partner_contact_gender/README.rst
odoo/addons/partner_contact_gender/models/res_partner.py
odoo/addons/partner_contact_gender/models/__init__.py
odoo/addons/partner_contact_gender/i18n/it.po
odoo/addons/partner_contact_gender/i18n/es.po
odoo/addons/partner_contact_gender/i18n/partner_gender.pot
odoo/addons/partner_contact_gender/i18n/sl.po
odoo/addons/partner_contact_gender/i18n/da.po
odoo/addons/partner_contact_gender/i18n/nl.po
odoo/addons/partner_contact_gender/i18n/de.po
odoo/addons/partner_contact_gender/i18n/fr.po
odoo/addons/partner_contact_gender/i18n/pt_BR.po
odoo/addons/partner_contact_gender/i18n/hr_HR.po
odoo/addons/partner_contact_gender/views/res_partner.xml
odoo/addons/partner_contact_gender/tests/__init__.py
odoo/addons/partner_contact_gender/tests/test_partner_contact_gender.py
odoo/addons/partner_contact_gender/static/description/icon.svg
odoo/addons/partner_contact_gender/static/description/icon.png
