Metadata-Version: 2.0
Name: odoo10-addon-partner-contact-gender
Version: 10.0.1.1.0
Summary: Add gender field to contacts
Home-page: https://www.tecnativa.com/
Author: UNKNOWN
Author-email: UNKNOWN
License: AGPL-3
Platform: UNKNOWN
Requires-Dist: odoo (<10.1dev,>=10.0)
Requires-Dist: odoo10-addon-partner-contact-personal-information-page
Classifier: Programming Language :: Python :: 2.7
Classifier: Framework :: Odoo
Classifier: License :: OSI Approved :: GNU Affero General Public License v3
